CHANGES.rst
INSTALL.rst
MANIFEST.in
README.rst
buildout.cfg
minitage.cfg
setup.cfg
setup.py
test.cfg
src/etc/minimerge.cfg
src/minitage/__init__.py
src/minitage.egg-info/PKG-INFO
src/minitage.egg-info/SOURCES.txt
src/minitage.egg-info/dependency_links.txt
src/minitage.egg-info/entry_points.txt
src/minitage.egg-info/namespace_packages.txt
src/minitage.egg-info/not-zip-safe
src/minitage.egg-info/requires.txt
src/minitage.egg-info/top_level.txt
src/minitage/core/__init__.py
src/minitage/core/api.py
src/minitage/core/cli.py
src/minitage/core/collections.py
src/minitage/core/common.py
src/minitage/core/core.py
src/minitage/core/distribute_setup.py
src/minitage/core/interfaces.py
src/minitage/core/objects.py
src/minitage/core/testing.py
src/minitage/core/update.py
src/minitage/core/version.py
src/minitage/core/cfgs/minibuild
src/minitage/core/cfgs/addon/.gitignore
src/minitage/core/cfgs/addon/.travis.yml
src/minitage/core/cfgs/addon/base.cfg
src/minitage/core/cfgs/addon/bootstrap.py
src/minitage/core/cfgs/addon/buildout.cfg
src/minitage/core/cfgs/addon/test-4.0.x.cfg
src/minitage/core/cfgs/addon/test-4.1.x.cfg
src/minitage/core/cfgs/addon/test-4.2.x.cfg
src/minitage/core/cfgs/addon/test-4.3.x.cfg
src/minitage/core/cfgs/addon/test-4.4.x.cfg
src/minitage/core/cfgs/addon/travis.cfg
src/minitage/core/cfgs/wrap/b.sh
src/minitage/core/cfgs/wrap/minitage.cfg
src/minitage/core/cfgs/wrap/minitage26.cfg
src/minitage/core/cfgs/wrap/minitage27.cfg
src/minitage/core/cfgs/wrap/minitagezeo.cfg
src/minitage/core/fetchers/__init__.py
src/minitage/core/fetchers/interfaces.py
src/minitage/core/fetchers/scm.py
src/minitage/core/fetchers/static.py
src/minitage/core/launchers/__init__.py
src/minitage/core/launchers/minimerge.py
src/minitage/core/launchers/minitagize.py
src/minitage/core/makers/__init__.py
src/minitage/core/makers/buildout.py
src/minitage/core/makers/interfaces.py
src/minitage/core/tests/__init__.py
src/minitage/core/tests/base.py
src/minitage/core/tests/bzr_fetcher.rst
src/minitage/core/tests/git_fetcher.rst
src/minitage/core/tests/hg_fetcher.rst
src/minitage/core/tests/minimerge_10.cfg
src/minitage/core/tests/static_fetcher.rst
src/minitage/core/tests/svn_fetcher.rst
src/minitage/core/tests/test_cli.py
src/minitage/core/tests/test_collections.py
