Metadata-Version: 1.1
Name: minitage
Version: 2.0.67
Summary: A meta package-manager to deploy projects on UNIX Systemes sponsored by Makina Corpus.
Home-page: http://cheeseshop.python.org/pypi/minitage
Author: Mathieu Le Marec - Pasquet
Author-email: kiorky@cryptelium.net
License: BSD
Platform: UNKNOWN
Classifier: Framework :: Buildout
Classifier: Intended Audience :: Developers
Classifier: License :: OSI Approved :: BSD License
Classifier: Topic :: Software Development :: Build Tools
Classifier: Topic :: Software Development :: Libraries :: Python Modules
